logfire_lsp/__init__.py
logfire_lsp/__main__.py
logfire_lsp/models.py
logfire_lsp/py.typed
logfire_lsp/utils.py
logfire_lsp/visitor.py
logfire_lsp/server/__init__.py
logfire_lsp/server/server.py
logfire_lsp-0.0.4.dist-info/METADATA
logfire_lsp-0.0.4.dist-info/WHEEL
logfire_lsp-0.0.4.dist-info/licenses/LICENSE
logfire_lsp-0.0.4.dist-info/RECORD
