Metadata-Version: 2.4
Name: logfire-lsp
Version: 0.0.4
Summary: A Language Server Protocol implementation for Pydantic Logfire
Author-email: Victorien Plot <contact@vctrn.dev>
License-Expression: MIT
License-File: LICENSE
Classifier: Development Status :: 3 - Alpha
Classifier: Intended Audience :: Developers
Classifier: Programming Language :: Python
Classifier: Programming Language :: Python :: 3
Classifier: Programming Language :: Python :: 3 :: Only
Classifier: Programming Language :: Python :: 3.9
Classifier: Programming Language :: Python :: 3.10
Classifier: Programming Language :: Python :: 3.11
Classifier: Programming Language :: Python :: 3.12
Classifier: Programming Language :: Python :: 3.13
Classifier: Programming Language :: Python :: 3.14
Classifier: Programming Language :: Python :: Implementation :: CPython
Classifier: Topic :: Software Development :: Libraries :: Python Modules
Classifier: Typing :: Typed
Requires-Python: >=3.9
Requires-Dist: libcst>=1.8.0
Requires-Dist: pygls>=2.0.0a4
Requires-Dist: typing-extensions>=4.10.0
